s93_test_automation/__init__.py
s93_test_automation/__main__.py
s93_test_automation/common.py
s93_test_automation/run_tests.py
s93_test_automation/data/files/over_6mb/bmp/bmp_6.12mb.bmp
s93_test_automation/data/files/under_6mb/bmp/bmp_32kb.bmp
s93_test_automation/data/files/under_6mb/bmp/bmp_5.93mb.bmp
s93_test_automation/data/files/under_6mb/corrupt/Corrupted_jpeg_png_mag_no
s93_test_automation/data/files/under_6mb/doc/doc_embedded_images_12kb.docx
s93_test_automation/data/files/under_6mb/harmless_macro/xls/CalcTest.xls
s93_test_automation/data/files/under_6mb/txt/txt_1kb.txt
s93_test_automation/integration_tests/__init__.py
s93_test_automation/integration_tests/rebuild/__init__.py
s93_test_automation/integration_tests/rebuild/jwt_token/__init__.py
s93_test_automation/integration_tests/rebuild/jwt_token/test_rebuild_jwt_base64.py
s93_test_automation/integration_tests/rebuild/jwt_token/test_rebuild_jwt_file.py
s93_test_automation/integration_tests/rebuild/jwt_token/test_rebuild_jwt_url.py
s93_test_automation/integration_tests/rebuild/x_api_key/__init__.py
s93_test_automation/integration_tests/rebuild/x_api_key/test_rebuild_xapi_base64.py
s93_test_automation/integration_tests/rebuild/x_api_key/test_rebuild_xapi_file.py
s93_test_automation/integration_tests/rebuild/x_api_key/test_rebuild_xapi_url.py
glasswall_aws_product_test_automation-1.1.0.dist-info/LICENSE
glasswall_aws_product_test_automation-1.1.0.dist-info/METADATA
glasswall_aws_product_test_automation-1.1.0.dist-info/WHEEL
glasswall_aws_product_test_automation-1.1.0.dist-info/entry_points.txt
glasswall_aws_product_test_automation-1.1.0.dist-info/top_level.txt
glasswall_aws_product_test_automation-1.1.0.dist-info/RECORD
