Metadata-Version: 2.1
Name: glasswall-aws-product-test-automation
Version: 1.1.0
Summary: A small package for testing Glasswall AWS products
Home-page: https://github.com/filetrust/aws-product-test-automation
Author: AngusWR
Author-email: aroberts@glasswallsolutions.com
License: UNKNOWN
Platform: UNKNOWN
Classifier: Programming Language :: Python :: 3.8
Requires-Python: >=3.6
Requires-Dist: requests (>=2.22.0)
